blackoil_pvt/__init__.py
blackoil_pvt/constants.py
blackoil_pvt/pvt_properties.py
blackoil_pvt/utilities.py
blackoil_pvt-0.1.0.dist-info/LICENSE
blackoil_pvt-0.1.0.dist-info/METADATA
blackoil_pvt-0.1.0.dist-info/WHEEL
blackoil_pvt-0.1.0.dist-info/top_level.txt
blackoil_pvt-0.1.0.dist-info/RECORD
