Metadata-Version: 2.1
Name: blackoil_pvt
Version: 0.1.0
Summary: A library for calculating black oil PVT properties using the Standing method.
Home-page: https://github.com/MElSersy/blackoil-pvt
Author: Mohamed ElSersy
Author-email: mrsersy@gmail.com
Classifier: Programming Language :: Python :: 3
Classifier: License :: OSI Approved :: MIT License
Classifier: Operating System :: OS Independent
Requires-Python: >=3.7
License-File: LICENSE
